<AssetBase>
	<Action dirCopy="../Ships/Common/img/customizeUI" destination="img/customizeUI" />
	<Action dirCopy="../Ships/Common/img/ship" destination="img/ship" prefix="second_" />	
	<Action randomizeHook="../Crew Pool/meta_crew_pool.xml" multiRand=""/>
	<Action randomizeHook="arti_fed_name.xml" multiRand=""/>
	<!-- The following are ship specific re-randomizations -->
	<!-- Kestral -->
	<Action randomizeHook="../Weapon Data/meta_weapon_pool_kes.xml" multiRand=""/>
	<Action randomizeHook="../System Pool/meta_system_pool_kes.xml" multiRand=""/>
	<Action selectDir="../Layouts/Kestrel" destination="data" metaData="meta_data.xml" prefix="second_" uniqueSelect="" />
	<Action selectDir="../Ships/Kestrel" destination="img/ship" metaData="meta_data.txt" prefix="second_" uniqueSelect="" />
	<!-- Engi -->
	<Action randomizeHook="../Weapon Data/meta_weapon_pool_eng.xml" multiRand=""/>
	<Action randomizeHook="../System Pool/meta_system_pool_eng.xml" multiRand=""/>
	<Action selectDir="../Layouts/Engi" destination="data" metaData="meta_data.xml" prefix="second_" uniqueSelect="" />
	<Action selectDir="../Ships/Engi" destination="img/ship" metaData="meta_data.txt" prefix="second_" uniqueSelect="" />
	<!-- Stealth -->
	<Action randomizeHook="../Weapon Data/meta_weapon_pool_stl.xml" multiRand=""/>
	<Action randomizeHook="../System Pool/meta_system_pool_stl.xml" multiRand=""/>
	<Action selectDir="../Layouts/Stealth" destination="data" metaData="meta_data.xml" prefix="second_" uniqueSelect="" />
	<Action selectDir="../Ships/Stealth" destination="img/ship" metaData="meta_data.txt" prefix="second_" uniqueSelect="" />
	<!-- Rock -->
	<Action randomizeHook="../Weapon Data/meta_weapon_pool_rck.xml" multiRand=""/>
	<Action randomizeHook="../System Pool/meta_system_pool_rck.xml" multiRand=""/>
	<Action selectDir="../Layouts/Rock" destination="data" metaData="meta_data.xml" prefix="second_" uniqueSelect="" />
	<Action selectDir="../Ships/Rock" destination="img/ship" metaData="meta_data.txt" prefix="second_" uniqueSelect="" />
	<!-- Mantis -->
	<Action randomizeHook="../Weapon Data/meta_weapon_pool_mts.xml" multiRand=""/>
	<Action randomizeHook="../System Pool/meta_system_pool_mts.xml" multiRand=""/>
	<Action selectDir="../Layouts/Mantis" destination="data" metaData="meta_data.xml" prefix="second_" uniqueSelect="" />
	<Action selectDir="../Ships/Mantis" destination="img/ship" metaData="meta_data.txt" prefix="second_" uniqueSelect="" />
	<!-- Fed -->
	<Action randomizeHook="../Weapon Data/meta_weapon_pool_fed.xml" multiRand=""/>
	<Action randomizeHook="../System Pool/meta_system_pool_fed.xml" multiRand=""/>
	<Action selectDir="../Layouts/Fed" destination="data" metaData="meta_data.xml" prefix="second_" uniqueSelect="" />
	<Action selectDir="../Ships/Fed" destination="img/ship" metaData="meta_data.txt" prefix="second_" uniqueSelect="" />
	<!-- Slug -->
	<Action randomizeHook="../Weapon Data/meta_weapon_pool_slg.xml" multiRand=""/>
	<Action randomizeHook="../System Pool/meta_system_pool_slg.xml" multiRand=""/>
	<Action selectDir="../Layouts/Slug" destination="data" metaData="meta_data.xml" prefix="second_" uniqueSelect="" />
	<Action selectDir="../Ships/Slug" destination="img/ship" metaData="meta_data.txt" prefix="second_" uniqueSelect="" />
	<!-- Zoltan -->
	<Action randomizeHook="../Weapon Data/meta_weapon_pool_zlt.xml" multiRand=""/>
	<Action randomizeHook="../System Pool/meta_system_pool_zlt.xml" multiRand=""/>
	<Action selectDir="../Layouts/Zoltan" destination="data" metaData="meta_data.xml" prefix="second_" uniqueSelect="" />
	<Action selectDir="../Ships/Zoltan" destination="img/ship" metaData="meta_data.txt" prefix="second_" uniqueSelect="" />
	<!-- Crystal -->
	<Action randomizeHook="../Weapon Data/meta_weapon_pool_ctl.xml" multiRand=""/>
	<Action randomizeHook="../System Pool/meta_system_pool_ctl.xml" multiRand=""/>
	<Action selectDir="../Layouts/Crystal" destination="data" metaData="meta_data.xml" prefix="second_" uniqueSelect="" />
	<Action selectDir="../Ships/Crystal" destination="img/ship" metaData="meta_data.txt" prefix="second_" uniqueSelect="" />
	<!-- Lanius -->
	<Action randomizeHook="../Weapon Data/meta_weapon_pool_lns.xml" multiRand=""/>
	<Action randomizeHook="../System Pool/meta_system_pool_lns.xml" multiRand=""/>
	<Action selectDir="../Layouts/Lanius" destination="data" metaData="meta_data.xml" prefix="second_" uniqueSelect="" />
	<Action selectDir="../Ships/Lanius" destination="img/ship" metaData="meta_data.txt" prefix="second_" uniqueSelect="" />
	
	<!-- Append skeleton files for secondary ships -->
	<Action skeletonAppend="blueprints.xml.append" destination="data" />
	<Action skeletonAppend="dlcBlueprints.xml.append" destination="data" />	
</AssetBase>